webbean/__init__.py
webbean/__main__.py
webbean/bank.py
webbean/core/Transaction.py
webbean/core/__init__.py
webbean/modules/Account.py
webbean/modules/MODULES.py
webbean/modules/__init__.py
webbean/modules/beancount.py
webbean/modules/weboob.py
webbean/resources/template/beancount.jinja
Webbean-0.0.1.dist-info/METADATA
Webbean-0.0.1.dist-info/WHEEL
Webbean-0.0.1.dist-info/entry_points.txt
Webbean-0.0.1.dist-info/top_level.txt
Webbean-0.0.1.dist-info/RECORD
