Metadata-Version: 2.1
Name: Webbean
Version: 0.0.1
Summary: An application to get transactions diffbetween accounting file and bank
Home-page: http://packages.python.org/webbean
Author: Pesche Romain
Author-email: rpesche@pesche.fr
License: GNU AGPL 3
Keywords: accounting weboob synchronization
Platform: UNKNOWN
Classifier: Development Status :: 1 - Planning
Classifier: Environment :: Console
Classifier: Topic :: Office/Business :: Financial :: Accounting
Classifier: Intended Audience :: End Users/Desktop
Classifier: License :: OSI Approved :: GNU Affero General Public License v3
Classifier: Programming Language :: Python :: 3 :: Only
Classifier: License :: OSI Approved :: BSD License
Requires-Dist: beancount
Requires-Dist: weboob (==1.3)
Requires-Dist: Jinja2 (==2.10.3)
Requires-Dist: Unidecode (==1.1.1)
